{ 
    "header":{ 
       "id":"1",
       "prepared":"2019-12-15T18:20:01.4106007Z",
       "sender":{ 
          "id": "Truth101",
          "name": "truth101"
       },
       "links":[]
    },
    "dataSets":[ 
       { 
            "action":"Information",
            "observations":{ 
                "0:0:0:0:0:0": [
                    12.5773,
                    0,
                    null
                ],
                "0:1:0:0:0:0": [
                    7.6020,
                    0,
                    null
                ],
                "0:2:0:0:0:0": [
                    11.6380,
                    0,
                    null
                ],
                "0:3:0:0:0:0": [
                    8.9843,
                    0,
                    null
                ],
                "1:0:0:0:0:0": [
                    8.6238,
                    0,
                    null
                ],
                "1:1:0:0:0:0": [
                    6.8710,
                    0,
                    null
                ],
                "1:2:0:0:0:0": [
                    16.0270,
                    0,
                    null
                ],
                "1:3:0:0:0:0": [
                    11.4280,
                    0,
                    null
                ],
                "2:0:0:0:0:0": [
                    9.9145,
                    0,
                    null
                ],
                "2:1:0:0:0:0": [
                    7.6220,
                    0,
                    null
                ],
                "2:2:0:0:0:0": [
                    9.2340,
                    0,
                    null
                ],
                "2:3:0:0:0:0": [
                    6.7353,
                    0,
                    null
                ],
                "3:0:0:0:0:0": [
                    12.4623,
                    0,
                    null
                ],
                "3:1:0:0:0:0": [
                    4.3890,
                    0,
                    null
                ],
                "3:2:0:0:0:0": [
                    13.5180,
                    0,
                    null
                ],
                "3:3:0:0:0:0": [
                    11.0705,
                    0,
                    null
                ],
                "4:0:0:0:0:0": [
                    26.9614,
                    0,
                    null
                ],
                "4:1:0:0:0:0": [
                    10.9610,
                    0,
                    null
                ],
                "4:2:0:0:0:0": [
                    8.6000,
                    0,
                    null
                ],
                "4:3:0:0:0:0": [
                    10.3367,
                    0,
                    null
                ],
                "5:0:0:0:0:0": [
                    25.8030,
                    0,
                    null
                ],
                "5:1:0:0:0:0": [
                    14.0600,
                    0,
                    null
                ],
                "5:2:0:0:0:0": [
                    13.3130,
                    0,
                    null
                ],
                "5:3:0:0:0:0": [
                    17.4125,
                    0,
                    null
                ],
                "6:0:0:0:0:0": [
                    19.0317,
                    0,
                    null
                ],
                "6:1:0:0:0:0": [
                    6.8010,
                    0,
                    null
                ],
                "6:2:0:0:0:0": [
                    10.4430,
                    0,
                    null
                ],
                "6:3:0:0:0:0": [
                    13.0941,
                    0,
                    null
                ],
                "7:0:0:0:0:0": [
                    9.2285,
                    0,
                    null
                ],
                "7:1:0:0:0:0": [
                    5.8850,
                    0,
                    null
                ],
                "7:2:0:0:0:0": [
                    6.6880,
                    0,
                    null
                ],
                "7:3:0:0:0:0": [
                    4.8896,
                    0,
                    null
                ],
                "8:0:0:0:0:0": [
                    12.8265,
                    0,
                    null
                ],
                "8:1:0:0:0:0": [
                    5.8480,
                    0,
                    null
                ],
                "8:2:0:0:0:0": [
                    6.8860,
                    0,
                    null
                ],
                "8:3:0:0:0:0": [
                    4.8700,
                    0,
                    null
                ],
                "9:0:0:0:0:0": [
                    9.8252,
                    0,
                    null
                ],
                "9:1:0:0:0:0": [
                    7.1300,
                    0,
                    null
                ],
                "9:2:0:0:0:0": [
                    8.3560,
                    0,
                    null
                ],
                "9:3:0:0:0:0": [
                    8.4659,
                    0,
                    null
                ],
                "10:0:0:0:0:0": [
                    4.7364,
                    0,
                    null
                ],
                "10:1:0:0:0:0": [
                    2.3020,
                    0,
                    null
                ],
                "10:2:0:0:0:0": [
                    2.7180,
                    0,
                    null
                ],
                "10:3:0:0:0:0": [
                    1.3267,
                    0,
                    null
                ],
                "11:0:0:0:0:0": [
                    9.4278,
                    0,
                    null
                ],
                "11:1:0:0:0:0": [
                    8.0450,
                    0,
                    null
                ],
                "11:2:0:0:0:0": [
                    11.8710,
                    0,
                    null
                ],
                "11:3:0:0:0:0": [
                    11.1442,
                    0,
                    null
                ],
                "12:0:0:0:0:0": [
                    11.1830,
                    0,
                    null
                ],
                "12:1:0:0:0:0": [
                    9.2670,
                    0,
                    null
                ],
                "12:2:0:0:0:0": [
                    9.9260,
                    0,
                    null
                ],
                "12:3:0:0:0:0": [
                    9.1261,
                    0,
                    null
                ],
                "13:0:0:0:0:0": [
                    7.9432,
                    0,
                    null
                ],
                "13:1:0:0:0:0": [
                    5.7040,
                    0,
                    null
                ],
                "13:2:0:0:0:0": [
                    6.6240,
                    0,
                    null
                ],
                "13:3:0:0:0:0": [
                    7.2260,
                    0,
                    null
                ],
                "14:0:0:0:0:0": [
                    17.3433,
                    0,
                    null
                ],
                "14:1:0:0:0:0": [
                    9.1850,
                    0,
                    null
                ],
                "14:2:0:0:0:0": [
                    18.7960,
                    0,
                    null
                ],
                "14:3:0:0:0:0": [
                    15.4708,
                    0,
                    null
                ],
                "15:0:0:0:0:0": [
                    13.2617,
                    0,
                    null
                ],
                "15:1:0:0:0:0": [
                    6.1280,
                    0,
                    null
                ],
                "15:2:0:0:0:0": [
                    6.7780,
                    0,
                    null
                ],
                "15:3:0:0:0:0": [
                    6.5967,
                    0,
                    null
                ],
                "16:0:0:0:0:0": [
                    9.7200,
                    0,
                    null
                ],
                "16:1:0:0:0:0": [
                    2.5420,
                    0,
                    null
                ],
                "16:2:0:0:0:0": [
                    6.7090,
                    0,
                    null
                ],
                "16:3:0:0:0:0": [
                    6.8192,
                    0,
                    null
                ],
                "17:0:0:0:0:0": [
                    17.8637,
                    0,
                    null
                ],
                "17:1:0:0:0:0": [
                    10.3180,
                    0,
                    null
                ],
                "17:2:0:0:0:0": [
                    9.5930,
                    0,
                    null
                ],
                "17:3:0:0:0:0": [
                    8.3209,
                    0,
                    null
                ],
                "18:0:0:0:0:0": [
                    5.7349,
                    0,
                    null
                ],
                "18:1:0:0:0:0": [
                    3.5580,
                    0,
                    null
                ],
                "18:2:0:0:0:0": [
                    4.8230,
                    0,
                    null
                ],
                "18:3:0:0:0:0": [
                    5.7233,
                    0,
                    null
                ],
                "19:0:0:0:0:0": [
                    13.3658,
                    0,
                    null
                ],
                "19:1:0:0:0:0": [
                    8.7130,
                    0,
                    null
                ],
                "19:2:0:0:0:0": [
                    8.4400,
                    0,
                    null
                ],
                "19:3:0:0:0:0": [
                    7.0525,
                    0,
                    null
                ]
            }
       }
    ],
    "structure":{ 
       "dimensions":{ 
            "observation":[ 
                { 
                "keyPosition":0,
                "id":"CANDIDATE",
                "name":"Candidate",
                "values":[ 
                    {
                        "id": "강민희",
                        "name": "강민희"
                    },
                    {
                        "id": "구정모",
                        "name": "구정모"
                    },
                    {
                        "id": "금동현",
                        "name": "금동현"
                    },
                    {
                        "id": "김민규",
                        "name": "김민규"
                    },
                    {
                        "id": "김요한",
                        "name": "김요한"
                    },
                    {
                        "id": "김우석",
                        "name": "김우석"
                    },
                    {
                        "id": "남도현",
                        "name": "남도현"
                    },
                    {
                        "id": "손동표",
                        "name": "손동표"
                    },
                    {
                        "id": "송유빈",
                        "name": "송유빈"
                    },
                    {
                        "id": "송형준",
                        "name": "송형준"
                    },
                    {
                        "id": "이세진",
                        "name": "이세진"
                    },
                    {
                        "id": "이은상",
                        "name": "이은상"
                    },
                    {
                        "id": "이진혁",
                        "name": "이진혁"
                    },
                    {
                        "id": "이한결",
                        "name": "이한결"
                    },
                    {
                        "id": "조승연",
                        "name": "조승연"
                    },
                    {
                        "id": "차준호",
                        "name": "차준호"
                    },
                    {
                        "id": "토니",
                        "name": "토니"
                    },
                    {
                        "id": "한승우",
                        "name": "한승우"
                    },
                    {
                        "id": "함원진",
                        "name": "함원진"
                    },
                    {
                        "id": "황윤성",
                        "name": "황윤성"
                    }
                ]
             },
             { 
                "id":"TIME_PERIOD",
                "name":"Time",
                "values":[ 
                   { 
                      "id":"1) Naver_TV_View",
                      "name":"1) Naver_TV_View"
                   },
                   { 
                      "id":"2) Naver_TV_Like",
                      "name":"2) Naver_TV_Like"
                   },
                   { 
                      "id":"3) DC_Inside_Frequency",
                      "name":"3) DC_Inside_Frequency"
                   },
                   { 
                      "id":"4) DC_Inside_Like",
                      "name":"4) DC_Inside_Like"
                   }
                ],
                "role":"TIME_PERIOD"
             },
             { 
                "keyPosition": 1,
                "id":"SEX",
                "name":"Sex",
                "values":[ 
                   { 
                      "id":"MW",
                      "name":"All persons"
                   }
                ]
             },
             { 
                "keyPosition": 2,
                "id":"AGE",
                "name":"Age",
                "values":[ 
                   { 
                      "id":"900000",
                      "name":"Total"
                   }
                ]
             },
             { 
                "keyPosition":3,
                "id":"SERIES",
                "name":"Series",
                "values":[ 
                   { 
                      "id":"UR",
                      "name":"Unemployment rate"
                   }
                ]
             },
             { 
                "keyPosition":4,
                "id":"FREQ",
                "name":"Frequency",
                "values":[ 
                   { 
                      "id":"A",
                      "name":"Annual"
                   }
                ]
             }
          ]
       },
       "attributes":{ 
          "dataSet":[ 
             { 
                "id":"UNIT",
                "name":"Unit",
                "values":[ 
                   { 
                      "id":"PC",
                      "name":"Percentage"
                   }
                ],
                "role":"UNIT_MEASURE"
             },
             { 
                "id":"POWERCODE",
                "name":"Unit multiplier",
                "values":[ 
                   { 
                      "id":"0",
                      "name":"Units"
                   }
                ],
                "role":"UNIT_MULT"
             },
             { 
                "id":"REFERENCEPERIOD",
                "name":"Reference period",
                "values":[ 
 
                ],
                "role":"BASE_PER"
             }
          ],
          "series":[ 
 
          ],
          "observation":[ 
             { 
                "id":"TIME_FORMAT",
                "name":"Time Format",
                "values":[ 
                   { 
                      "id":"P1Y",
                      "name":"Annual"
                   }
                ]
             },
             { 
                "id":"OBS_STATUS",
                "name":"Observation Status",
                "values":[ 
                ]
             }
          ]
       }
    }
 }